{
    "metadata": {
      "DEBUG": "false",
      "PROJECT_WORKSPACE": "springboot-kotlin",
      "ARTIFACT_OUTPUT": "true",
      "ARTIFACT_OUTPUT_DESTINATION": "build",
      "COMPUTE_TYPE": "SMALL"
    },
    "label": {
      "customer": "cayi",
      "project": "springboot-kotlin"
    },
    "git": {
      "owner": "kgumbs",
      "branch": "main",
      "repository": "shinto-samples",
      "codeStarId": "a16d91c5-2dd3-4ee4-89f9-4d5865c0a45c"
    },
    "buildSpec": {
      "type": "JAVA",
      "packageManager": "GRADLE",
      "codeScanType": ["CODACY","SNYK"]
    },
    "imageBuilder": {
      "type": "BUILDPACK",
      "enabled": true,
      "imageScanType": ["ECR","SNYK"],
      "env": {
        "IMAGESCAN_FINDINGS_DISABLED": "true"
      }
    }
}